momgrid/VerticalSplitScale.py
momgrid/__init__.py
momgrid/classes.py
momgrid/comparison.py
momgrid/external.py
momgrid/geoslice.py
momgrid/metadata.py
momgrid/plot.py
momgrid/util.py
momgrid/vertical.py
momgrid/xr_stats.py
momgrid/grids/WOA18_025deg_horiz_grid.nc
momgrid/grids/WOA18_1deg_horiz_grid.nc
momgrid-1.12.0.data/scripts/momcompare.py
momgrid-1.12.0.dist-info/licenses/LICENSE.txt
momgrid-1.12.0.dist-info/METADATA
momgrid-1.12.0.dist-info/WHEEL
momgrid-1.12.0.dist-info/top_level.txt
momgrid-1.12.0.dist-info/RECORD
